noex/__init__.py
noex/api.py
noex/exchange.py
noex/info.py
noex/websocket_client.py
noex/utils/__init__.py
noex/utils/constants.py
noex/utils/error.py
noex/utils/types.py
noex/utils/util.py
noex_sdk-1.0.0.dist-info/licenses/LICENSE
noex_sdk-1.0.0.dist-info/METADATA
noex_sdk-1.0.0.dist-info/WHEEL
noex_sdk-1.0.0.dist-info/top_level.txt
noex_sdk-1.0.0.dist-info/RECORD
